tests/__init__.py
tests/payment.py
tests/test_cards.py
vakifbank/Auth.py
vakifbank/Card.py
vakifbank/Payment.py
vakifbank/Routes.py
vakifbank/Service.py
vakifbank/ThreeD_Payment.py
vakifbank/Vpos.py
vakifbank/__init__.py
vakifbank/consts.py
vakifbank/error_codes.py
vakifbank/config/__init__.py
vakifbank/config/consts.py
vakifbank/config/error_codes.py
vakifbank/html/pareq_to_acs.html
vakifbank-0.1.3.dist-info/LICENSE
vakifbank-0.1.3.dist-info/METADATA
vakifbank-0.1.3.dist-info/WHEEL
vakifbank-0.1.3.dist-info/top_level.txt
vakifbank-0.1.3.dist-info/RECORD
