Metadata-Version: 2.1
Name: vakifbank
Version: 0.1.3
Summary: Vakıfbank Payment Gateway Python Package
Home-page: https://github.com/cKurultayKalkan/vakifbank-python.git
Author: Çağdaş Kurultay Kalkan
Author-email: kurultay@codeck.com.tr
License: UNKNOWN
Platform: UNKNOWN
Classifier: Programming Language :: Python :: 3
Classifier: License :: OSI Approved :: MIT License
Classifier: Operating System :: OS Independent
Requires-Python: >=3.6
Requires-Dist: xmltodict
Requires-Dist: requests
